learnify_ml/__init__.py
learnify_ml/config/__init__.py
learnify_ml/config/config_paths.py
learnify_ml/config/model_config.py
learnify_ml/src/__init__.py
learnify_ml/src/custom_exception.py
learnify_ml/src/data_preprocessing.py
learnify_ml/src/data_visualizer.py
learnify_ml/src/logger.py
learnify_ml/src/model_training.py
learnify_ml/src/model_training_engine.py
learnify_ml/training_pipeline/__init__.py
learnify_ml/training_pipeline/training_pipeline.py
learnify_ml/utils/__init__.py
learnify_ml/utils/common_functions.py
learnify_ml-0.0.28.dist-info/licenses/LICENSE
learnify_ml-0.0.28.dist-info/METADATA
learnify_ml-0.0.28.dist-info/WHEEL
learnify_ml-0.0.28.dist-info/top_level.txt
learnify_ml-0.0.28.dist-info/RECORD
