Metadata-Version: 2.4
Name: learnify_ml
Version: 0.0.28
Summary: A package for auto preprocessing and training machine learning models
Author: Yusuf Çakır
License-Expression: MIT
Project-URL: Homepage, https://github.com/cakiryusuff/learnify-ml
Project-URL: Issues, https://github.com/cakiryusuff/learnify-ml/issues
Classifier: Programming Language :: Python
Requires-Python: >=3.11
License-File: LICENSE
Requires-Dist: numpy
Requires-Dist: pandas
Requires-Dist: scikit-learn==1.6.1
Requires-Dist: lightgbm
Requires-Dist: xgboost==2.1.4
Requires-Dist: imbalanced-learn
Requires-Dist: statsmodels
Requires-Dist: tqdm
Requires-Dist: nltk
Requires-Dist: matplotlib
Requires-Dist: seaborn
Dynamic: license-file
